authorizenet/__init__.py
authorizenet/apicontractsv1.py
authorizenet/apicontrollers.py
authorizenet/apicontrollersbase.py
authorizenet/constants.py
authorizenet/utility.py
dms_authorizenet-0.0.1.dist-info/LICENSE.txt
dms_authorizenet-0.0.1.dist-info/METADATA
dms_authorizenet-0.0.1.dist-info/WHEEL
dms_authorizenet-0.0.1.dist-info/top_level.txt
dms_authorizenet-0.0.1.dist-info/RECORD
